MANIFEST.in
setup.py
msg_serv_13_21.egg-info/PKG-INFO
msg_serv_13_21.egg-info/SOURCES.txt
msg_serv_13_21.egg-info/dependency_links.txt
msg_serv_13_21.egg-info/requires.txt
msg_serv_13_21.egg-info/top_level.txt
server/__init__.py
server/server.py
server/common/__init__.py
server/common/constants.py
server/common/decos.py
server/common/descriptors.py
server/common/errors.py
server/common/functions.py
server/common/metacls.py
server/icons/delete.png
server/icons/exit.png
server/icons/history.png
server/icons/refresh.png
server/icons/register.png
server/icons/settings.png
server/log/__init__.py
server/log/log_config/__init__.py
server/log/log_config/server_log_config.py
server/project_tests/__init__.py
server/project_tests/test_client.py
server/project_tests/test_functions.py
server/project_tests/test_server.py
server/server/__init__.py
server/server/config_window.py
server/server/core.py
server/server/create_conf_file.py
server/server/delete_user_window.py
server/server/history_window.py
server/server/main_window.py
server/server/reg_user_window.py
server/server/server_database.py