Metadata-Version: 1.0
Name: msg-serv-13-21
Version: 0.1.9
Summary: The server part of the course project "Messenger"
Home-page: UNKNOWN
Author: Kostitsyn Aleksandr
Author-email: kostitsin.a@mail.ru
License: UNKNOWN
Platform: UNKNOWN
